README.md
setup.py
behave_plain_color_formatter/__init__.py
behave_plain_color_formatter.egg-info/PKG-INFO
behave_plain_color_formatter.egg-info/SOURCES.txt
behave_plain_color_formatter.egg-info/dependency_links.txt
behave_plain_color_formatter.egg-info/requires.txt
behave_plain_color_formatter.egg-info/top_level.txt