Metadata-Version: 2.1
Name: behave-plain-color-formatter
Version: 0.0.2
Summary: Formatter for behave that uses color but not fancy terminal repositioning
Home-page: https://github.com/msabramo/behave-plain-color-formatter
Author: Marc Abramowitz
Author-email: msabramo@gmail.com
License: MIT
Keywords: testing,behave,teamcity,formatter,report
Platform: UNKNOWN
Classifier: Development Status :: 5 - Production/Stable
Classifier: Intended Audience :: Developers
Classifier: License :: OSI Approved :: MIT License
Classifier: Topic :: Software Development :: Testing
Classifier: Topic :: Software Development :: Build Tools
Classifier: Topic :: Utilities
